afl.cpython-36m-darwin.so
python_afl_ph4-0.7.2.data/scripts/py-afl-cmin
python_afl_ph4-0.7.2.data/scripts/py-afl-fuzz
python_afl_ph4-0.7.2.data/scripts/py-afl-showmap
python_afl_ph4-0.7.2.data/scripts/py-afl-tmin
python_afl_ph4-0.7.2.dist-info/METADATA
python_afl_ph4-0.7.2.dist-info/RECORD
python_afl_ph4-0.7.2.dist-info/WHEEL
