Metadata-Version: 2.1
Name: python-afl-ph4
Version: 0.7.2
Summary: American Fuzzy Lop fork server and instrumentation for pure-Python code
Home-page: http://jwilk.net/software/python-afl
Author: Jakub Wilk
Author-email: jwilk@jwilk.net
License: MIT
Platform: UNKNOWN
Classifier: Development Status :: 3 - Alpha
Classifier: Intended Audience :: Developers
Classifier: License :: OSI Approved :: MIT License
Classifier: Operating System :: POSIX
Classifier: Programming Language :: Cython
Classifier: Programming Language :: Python :: 2
Classifier: Programming Language :: Python :: 3
Classifier: Topic :: Software Development :: Quality Assurance
Classifier: Topic :: Software Development :: Testing
